{
    "word_count": 599,
    "word_count_message": "There were 599 words in the input. We need a minimum of 600, preferably 1,200 or more, to compute statistically significant estimates",
    "processed_language": "en",
    "personality": [
        {
            "trait_id": "big5_openness",
            "name": "Openness",
            "category": "personality",
            "percentile": 0.9770213439134786,
            "raw_score": 0.8123708027604105,
            "significant": true,
            "children": [
                {
                    "trait_id": "facet_adventurousness",
                    "name": "Adventurousness",
                    "category": "personality",
                    "percentile": 0.54226099735757,
                    "raw_score": 0.5085923045622366,
                    "significant": true
                },
                {
                    "trait_id": "facet_artistic_interests",
                    "name": "Artistic interests",
                    "category": "personality",
                    "percentile": 0.9269246202583008,
                    "raw_score": 0.738893818354245,
                    "significant": true
                },
                {
                    "trait_id": "facet_emotionality",
                    "name": "Emotionality",
                    "category": "personality",
                    "percentile": 0.24291274449789824,
                    "raw_score": 0.619780698533489,
                    "significant": true
                },
                {
                    "trait_id": "facet_imagination",
                    "name": "Imagination",
                    "category": "personality",
                    "percentile": 0.7853595432097782,
                    "raw_score": 0.774119319642329,
                    "significant": true
                },
                {
                    "trait_id": "facet_intellect",
                    "name": "Intellect",
                    "category": "personality",
                    "percentile": 0.9959354048116328,
                    "raw_score": 0.7297526155771393,
                    "significant": true
                },
                {
                    "trait_id": "facet_liberalism",
                    "name": "Authority-challenging",
                    "category": "personality",
                    "percentile": 0.7456746022672056,
                    "raw_score": 0.5495184963611848,
                    "significant": true
                }
            ]
        },
        {
            "trait_id": "big5_conscientiousness",
            "name": "Conscientiousness",
            "category": "personality",
            "percentile": 0.24842156697468265,
            "raw_score": 0.5963601676426181,
            "significant": true,
            "children": [
                {
                    "trait_id": "facet_achievement_striving",
                    "name": "Achievement striving",
                    "category": "personality",
                    "percentile": 0.5012222570489918,
                    "raw_score": 0.6885606623372715,
                    "significant": true
                },
                {
                    "trait_id": "facet_cautiousness",
                    "name": "Cautiousness",
                    "category": "personality",
                    "percentile": 0.9594805199952574,
                    "raw_score": 0.6026079223209991,
                    "significant": true
                },
                {
                    "trait_id": "facet_dutifulness",
                    "name": "Dutifulness",
                    "category": "personality",
                    "percentile": 0.3095127184040054,
                    "raw_score": 0.6467233680906259,
                    "significant": true
                },
                {
                    "trait_id": "facet_orderliness",
                    "name": "Orderliness",
                    "category": "personality",
                    "percentile": 0.9897802913466378,
                    "raw_score": 0.5700900179988108,
                    "significant": true
                },
                {
                    "trait_id": "facet_self_discipline",
                    "name": "Self-discipline",
                    "category": "personality",
                    "percentile": 0.7020367356022151,
                    "raw_score": 0.5959134326439507,
                    "significant": true
                },
                {
                    "trait_id": "facet_self_efficacy",
                    "name": "Self-efficacy",
                    "category": "personality",
                    "percentile": 0.8943128052117082,
                    "raw_score": 0.7970527756828465,
                    "significant": true
                }
            ]
        },
        {
            "trait_id": "big5_extraversion",
            "name": "Extraversion",
            "category": "personality",
            "percentile": 0.24574480192520076,
            "raw_score": 0.5203077331860874,
            "significant": true,
            "children": [
                {
                    "trait_id": "facet_activity_level",
                    "name": "Activity level",
                    "category": "personality",
                    "percentile": 0.4616127077614365,
                    "raw_score": 0.5354480479262795,
                    "significant": true
                },
                {
                    "trait_id": "facet_assertiveness",
                    "name": "Assertiveness",
                    "category": "personality",
                    "percentile": 0.6898754916366975,
                    "raw_score": 0.6688288135301711,
                    "significant": true
                },
                {
                    "trait_id": "facet_cheerfulness",
                    "name": "Cheerfulness",
                    "category": "personality",
                    "percentile": 0.06588550020023437,
                    "raw_score": 0.5675595089789919,
                    "significant": true
                },
                {
                    "trait_id": "facet_excitement_seeking",
                    "name": "Excitement-seeking",
                    "category": "personality",
                    "percentile": 0.3905288331379754,
                    "raw_score": 0.5918195988338306,
                    "significant": true
                },
                {
                    "trait_id": "facet_friendliness",
                    "name": "Outgoing",
                    "category": "personality",
                    "percentile": 0.026780352938830132,
                    "raw_score": 0.46366972527561373,
                    "significant": true
                },
                {
                    "trait_id": "facet_gregariousness",
                    "name": "Gregariousness",
                    "category": "personality",
                    "percentile": 0.002626701777369622,
                    "raw_score": 0.30985305159823673,
                    "significant": true
                }
            ]
        },
        {
            "trait_id": "big5_agreeableness",
            "name": "Agreeableness",
            "category": "personality",
            "percentile": 0.0016822860862122369,
            "raw_score": 0.6256259798493676,
            "significant": true,
            "children": [
                {
                    "trait_id": "facet_altruism",
                    "name": "Altruism",
                    "category": "personality",
                    "percentile": 0.5902709026247427,
                    "raw_score": 0.7130964173446868,
                    "significant": true
                },
                {
                    "trait_id": "facet_cooperation",
                    "name": "Cooperation",
                    "category": "personality",
                    "percentile": 0.5358848788899507,
                    "raw_score": 0.5848157057209016,
                    "significant": true
                },
                {
                    "trait_id": "facet_modesty",
                    "name": "Modesty",
                    "category": "personality",
                    "percentile": 0.46107318401314623,
                    "raw_score": 0.443218807937388,
                    "significant": true
                },
                {
                    "trait_id": "facet_morality",
                    "name": "Uncompromising",
                    "category": "personality",
                    "percentile": 0.6160937190154108,
                    "raw_score": 0.6397414133385437,
                    "significant": true
                },
                {
                    "trait_id": "facet_sympathy",
                    "name": "Sympathy",
                    "category": "personality",
                    "percentile": 0.6174094124823526,
                    "raw_score": 0.6748832698848475,
                    "significant": true
                },
                {
                    "trait_id": "facet_trust",
                    "name": "Trust",
                    "category": "personality",
                    "percentile": 0.22676968627242816,
                    "raw_score": 0.5549233584767924,
                    "significant": true
                }
            ]
        },
        {
            "trait_id": "big5_neuroticism",
            "name": "Emotional range",
            "category": "personality",
            "percentile": 0.18124411251374728,
            "raw_score": 0.47277768683654153,
            "significant": true,
            "children": [
                {
                    "trait_id": "facet_anger",
                    "name": "Fiery",
                    "category": "personality",
                    "percentile": 0.20215627849211149,
                    "raw_score": 0.49011071805484385,
                    "significant": true
                },
                {
                    "trait_id": "facet_anxiety",
                    "name": "Prone to worry",
                    "category": "personality",
                    "percentile": 0.1059450340059429,
                    "raw_score": 0.5089756740086397,
                    "significant": true
                },
                {
                    "trait_id": "facet_depression",
                    "name": "Melancholy",
                    "category": "personality",
                    "percentile": 0.513890145261439,
                    "raw_score": 0.45064458674081653,
                    "significant": true
                },
                {
                    "trait_id": "facet_immoderation",
                    "name": "Immoderation",
                    "category": "personality",
                    "percentile": 0.17474302958537669,
                    "raw_score": 0.46463343758021647,
                    "significant": true
                },
                {
                    "trait_id": "facet_self_consciousness",
                    "name": "Self-consciousness",
                    "category": "personality",
                    "percentile": 0.4747618484105729,
                    "raw_score": 0.5433834842126559,
                    "significant": true
                },
                {
                    "trait_id": "facet_vulnerability",
                    "name": "Susceptible to stress",
                    "category": "personality",
                    "percentile": 0.1550784161519818,
                    "raw_score": 0.4029617134284914,
                    "significant": true
                }
            ]
        }
    ],
    "needs": [
        {
            "trait_id": "need_challenge",
            "name": "Challenge",
            "category": "needs",
            "percentile": 0.014673254132157698,
            "raw_score": 0.6340683874239346,
            "significant": true
        },
        {
            "trait_id": "need_closeness",
            "name": "Closeness",
            "category": "needs",
            "percentile": 0.01612720310550836,
            "raw_score": 0.6983186504063338,
            "significant": true
        },
        {
            "trait_id": "need_curiosity",
            "name": "Curiosity",
            "category": "needs",
            "percentile": 0.7457616642603435,
            "raw_score": 0.8340526759104567,
            "significant": true
        },
        {
            "trait_id": "need_excitement",
            "name": "Excitement",
            "category": "needs",
            "percentile": 0.15744954976360953,
            "raw_score": 0.6053726509150816,
            "significant": true
        },
        {
            "trait_id": "need_harmony",
            "name": "Harmony",
            "category": "needs",
            "percentile": 0.1511422985010794,
            "raw_score": 0.7736382289349264,
            "significant": true
        },
        {
            "trait_id": "need_ideal",
            "name": "Ideal",
            "category": "needs",
            "percentile": 0.021617148717719747,
            "raw_score": 0.5949916483423643,
            "significant": true
        },
        {
            "trait_id": "need_liberty",
            "name": "Liberty",
            "category": "needs",
            "percentile": 0.07663699145747821,
            "raw_score": 0.6830136492343366,
            "significant": true
        },
        {
            "trait_id": "need_love",
            "name": "Love",
            "category": "needs",
            "percentile": 0.10329395740224417,
            "raw_score": 0.7072201474446662,
            "significant": true
        },
        {
            "trait_id": "need_practicality",
            "name": "Practicality",
            "category": "needs",
            "percentile": 0.6940220446487714,
            "raw_score": 0.7387334596614226,
            "significant": true
        },
        {
            "trait_id": "need_self_expression",
            "name": "Self-expression",
            "category": "needs",
            "percentile": 0.4283740990700747,
            "raw_score": 0.6688123239738807,
            "significant": true
        },
        {
            "trait_id": "need_stability",
            "name": "Stability",
            "category": "needs",
            "percentile": 0.26157897166370303,
            "raw_score": 0.714115188149589,
            "significant": true
        },
        {
            "trait_id": "need_structure",
            "name": "Structure",
            "category": "needs",
            "percentile": 0.24404667812287478,
            "raw_score": 0.6772910871391784,
            "significant": true
        }
    ],
    "values": [
        {
            "trait_id": "value_conservation",
            "name": "Conservation",
            "category": "values",
            "percentile": 0.0032058332348974816,
            "raw_score": 0.5426455437422676,
            "significant": true
        },
        {
            "trait_id": "value_openness_to_change",
            "name": "Openness to change",
            "category": "values",
            "percentile": 0.3522325428299308,
            "raw_score": 0.7696418762039867,
            "significant": true
        },
        {
            "trait_id": "value_hedonism",
            "name": "Hedonism",
            "category": "values",
            "percentile": 0.04627516347706295,
            "raw_score": 0.6307064409287999,
            "significant": true
        },
        {
            "trait_id": "value_self_enhancement",
            "name": "Self-enhancement",
            "category": "values",
            "percentile": 0.0011815058689491065,
            "raw_score": 0.5729434430264043,
            "significant": true
        },
        {
            "trait_id": "value_self_transcendence",
            "name": "Self-transcendence",
            "category": "values",
            "percentile": 0.12559192424373472,
            "raw_score": 0.8142689505604186,
            "significant": true
        }
    ],
    "warnings": [
        {
            "warning_id": "WORD_COUNT_MESSAGE",
            "message": "There were 599 words in the input. We need a minimum of 600, preferably 1,200 or more, to compute statistically significant estimates"
        }
    ]
}