{
    "word_count": 687,
    "processed_language": "en",
    "personality": [
        {
            "trait_id": "big5_openness",
            "name": "Openness",
            "category": "personality",
            "percentile": 0.9835361457546716,
            "raw_score": 0.8167504729263084,
            "significant": true,
            "children": [
                {
                    "trait_id": "facet_adventurousness",
                    "name": "Adventurousness",
                    "category": "personality",
                    "percentile": 0.3037657273679529,
                    "raw_score": 0.48655084066910437,
                    "significant": true
                },
                {
                    "trait_id": "facet_artistic_interests",
                    "name": "Artistic interests",
                    "category": "personality",
                    "percentile": 0.9838699519235803,
                    "raw_score": 0.7737181416100145,
                    "significant": true
                },
                {
                    "trait_id": "facet_emotionality",
                    "name": "Emotionality",
                    "category": "personality",
                    "percentile": 0.48781704609107385,
                    "raw_score": 0.6469498712079345,
                    "significant": true
                },
                {
                    "trait_id": "facet_imagination",
                    "name": "Imagination",
                    "category": "personality",
                    "percentile": 0.8920296009113637,
                    "raw_score": 0.7963205586685401,
                    "significant": true
                },
                {
                    "trait_id": "facet_intellect",
                    "name": "Intellect",
                    "category": "personality",
                    "percentile": 0.9910458299010482,
                    "raw_score": 0.7168317024105835,
                    "significant": true
                },
                {
                    "trait_id": "facet_liberalism",
                    "name": "Authority-challenging",
                    "category": "personality",
                    "percentile": 0.7930188506421065,
                    "raw_score": 0.5573757175213336,
                    "significant": true
                }
            ]
        },
        {
            "trait_id": "big5_conscientiousness",
            "name": "Conscientiousness",
            "category": "personality",
            "percentile": 0.06902635363947512,
            "raw_score": 0.558878811089606,
            "significant": true,
            "children": [
                {
                    "trait_id": "facet_achievement_striving",
                    "name": "Achievement striving",
                    "category": "personality",
                    "percentile": 0.24514934534577204,
                    "raw_score": 0.6518755729991558,
                    "significant": true
                },
                {
                    "trait_id": "facet_cautiousness",
                    "name": "Cautiousness",
                    "category": "personality",
                    "percentile": 0.8750878618135737,
                    "raw_score": 0.5651169016635823,
                    "significant": true
                },
                {
                    "trait_id": "facet_dutifulness",
                    "name": "Dutifulness",
                    "category": "personality",
                    "percentile": 0.2194831918876139,
                    "raw_score": 0.6399468989149697,
                    "significant": true
                },
                {
                    "trait_id": "facet_orderliness",
                    "name": "Orderliness",
                    "category": "personality",
                    "percentile": 0.930806070376919,
                    "raw_score": 0.5426943013239414,
                    "significant": true
                },
                {
                    "trait_id": "facet_self_discipline",
                    "name": "Self-discipline",
                    "category": "personality",
                    "percentile": 0.36220644468884705,
                    "raw_score": 0.553858487532461,
                    "significant": true
                },
                {
                    "trait_id": "facet_self_efficacy",
                    "name": "Self-efficacy",
                    "category": "personality",
                    "percentile": 0.6693432890645665,
                    "raw_score": 0.7685069287614916,
                    "significant": true
                }
            ]
        },
        {
            "trait_id": "big5_extraversion",
            "name": "Extraversion",
            "category": "personality",
            "percentile": 0.3711140541669222,
            "raw_score": 0.5363292631678382,
            "significant": true,
            "children": [
                {
                    "trait_id": "facet_activity_level",
                    "name": "Activity level",
                    "category": "personality",
                    "percentile": 0.3879113918949662,
                    "raw_score": 0.5258080790059277,
                    "significant": true
                },
                {
                    "trait_id": "facet_assertiveness",
                    "name": "Assertiveness",
                    "category": "personality",
                    "percentile": 0.4496858273198119,
                    "raw_score": 0.6377372410385762,
                    "significant": true
                },
                {
                    "trait_id": "facet_cheerfulness",
                    "name": "Cheerfulness",
                    "category": "personality",
                    "percentile": 0.02844453066159519,
                    "raw_score": 0.55423627893252,
                    "significant": true
                },
                {
                    "trait_id": "facet_excitement_seeking",
                    "name": "Excitement-seeking",
                    "category": "personality",
                    "percentile": 0.42449172353368325,
                    "raw_score": 0.5955306821973534,
                    "significant": true
                },
                {
                    "trait_id": "facet_friendliness",
                    "name": "Outgoing",
                    "category": "personality",
                    "percentile": 0.011140881802201297,
                    "raw_score": 0.4458565936713088,
                    "significant": true
                },
                {
                    "trait_id": "facet_gregariousness",
                    "name": "Gregariousness",
                    "category": "personality",
                    "percentile": 0.002826384326005904,
                    "raw_score": 0.31107657740116984,
                    "significant": true
                }
            ]
        },
        {
            "trait_id": "big5_agreeableness",
            "name": "Agreeableness",
            "category": "personality",
            "percentile": 0.0006312441164139093,
            "raw_score": 0.6140149040627851,
            "significant": true,
            "children": [
                {
                    "trait_id": "facet_altruism",
                    "name": "Altruism",
                    "category": "personality",
                    "percentile": 0.5723066741102978,
                    "raw_score": 0.7114829816975332,
                    "significant": true
                },
                {
                    "trait_id": "facet_cooperation",
                    "name": "Cooperation",
                    "category": "personality",
                    "percentile": 0.45112180948461666,
                    "raw_score": 0.5719890250866757,
                    "significant": true
                },
                {
                    "trait_id": "facet_modesty",
                    "name": "Modesty",
                    "category": "personality",
                    "percentile": 0.4759131477293142,
                    "raw_score": 0.4451878950813202,
                    "significant": true
                },
                {
                    "trait_id": "facet_morality",
                    "name": "Uncompromising",
                    "category": "personality",
                    "percentile": 0.38724974110465527,
                    "raw_score": 0.6122929338605091,
                    "significant": true
                },
                {
                    "trait_id": "facet_sympathy",
                    "name": "Sympathy",
                    "category": "personality",
                    "percentile": 0.7160799372334206,
                    "raw_score": 0.6852904850955479,
                    "significant": true
                },
                {
                    "trait_id": "facet_trust",
                    "name": "Trust",
                    "category": "personality",
                    "percentile": 0.15707560365922774,
                    "raw_score": 0.5443347574265041,
                    "significant": true
                }
            ]
        },
        {
            "trait_id": "big5_neuroticism",
            "name": "Emotional range",
            "category": "personality",
            "percentile": 0.8694211252793103,
            "raw_score": 0.6274114496338411,
            "significant": true,
            "children": [
                {
                    "trait_id": "facet_anger",
                    "name": "Fiery",
                    "category": "personality",
                    "percentile": 0.5206112821176023,
                    "raw_score": 0.5385421222571152,
                    "significant": true
                },
                {
                    "trait_id": "facet_anxiety",
                    "name": "Prone to worry",
                    "category": "personality",
                    "percentile": 0.47584928183509645,
                    "raw_score": 0.5899809198580128,
                    "significant": true
                },
                {
                    "trait_id": "facet_depression",
                    "name": "Melancholy",
                    "category": "personality",
                    "percentile": 0.8035670586372443,
                    "raw_score": 0.5025569211262901,
                    "significant": true
                },
                {
                    "trait_id": "facet_immoderation",
                    "name": "Immoderation",
                    "category": "personality",
                    "percentile": 0.24695497237893677,
                    "raw_score": 0.47429906354925805,
                    "significant": true
                },
                {
                    "trait_id": "facet_self_consciousness",
                    "name": "Self-consciousness",
                    "category": "personality",
                    "percentile": 0.6749284341404971,
                    "raw_score": 0.5705807910804921,
                    "significant": true
                },
                {
                    "trait_id": "facet_vulnerability",
                    "name": "Susceptible to stress",
                    "category": "personality",
                    "percentile": 0.5945978229937956,
                    "raw_score": 0.4828735644214996,
                    "significant": true
                }
            ]
        }
    ],
    "needs": [
        {
            "trait_id": "need_challenge",
            "name": "Challenge",
            "category": "needs",
            "percentile": 0.0005295863838079562,
            "raw_score": 0.5849360474583675,
            "significant": true
        },
        {
            "trait_id": "need_closeness",
            "name": "Closeness",
            "category": "needs",
            "percentile": 0.017268110687613303,
            "raw_score": 0.6995387815495258,
            "significant": true
        },
        {
            "trait_id": "need_curiosity",
            "name": "Curiosity",
            "category": "needs",
            "percentile": 0.6377880475049273,
            "raw_score": 0.8259290745110923,
            "significant": true
        },
        {
            "trait_id": "need_excitement",
            "name": "Excitement",
            "category": "needs",
            "percentile": 0.11984104158938969,
            "raw_score": 0.5918061651607283,
            "significant": true
        },
        {
            "trait_id": "need_harmony",
            "name": "Harmony",
            "category": "needs",
            "percentile": 0.12308456183928762,
            "raw_score": 0.7692129163716888,
            "significant": true
        },
        {
            "trait_id": "need_ideal",
            "name": "Ideal",
            "category": "needs",
            "percentile": 0.022779568249439386,
            "raw_score": 0.5960363880780357,
            "significant": true
        },
        {
            "trait_id": "need_liberty",
            "name": "Liberty",
            "category": "needs",
            "percentile": 0.061308950438808074,
            "raw_score": 0.6786749622399484,
            "significant": true
        },
        {
            "trait_id": "need_love",
            "name": "Love",
            "category": "needs",
            "percentile": 0.2708368683379,
            "raw_score": 0.7389721625635057,
            "significant": true
        },
        {
            "trait_id": "need_practicality",
            "name": "Practicality",
            "category": "needs",
            "percentile": 0.47720633275990093,
            "raw_score": 0.7265382007721578,
            "significant": true
        },
        {
            "trait_id": "need_self_expression",
            "name": "Self-expression",
            "category": "needs",
            "percentile": 0.4476752080175934,
            "raw_score": 0.6705018798738586,
            "significant": true
        },
        {
            "trait_id": "need_stability",
            "name": "Stability",
            "category": "needs",
            "percentile": 0.1208278988623383,
            "raw_score": 0.6971606971430051,
            "significant": true
        },
        {
            "trait_id": "need_structure",
            "name": "Structure",
            "category": "needs",
            "percentile": 0.039642241715669824,
            "raw_score": 0.6485275317807095,
            "significant": true
        }
    ],
    "values": [
        {
            "trait_id": "value_conservation",
            "name": "Conservation",
            "category": "values",
            "percentile": 0.0017119563963651774,
            "raw_score": 0.5335940769982876,
            "significant": true
        },
        {
            "trait_id": "value_openness_to_change",
            "name": "Openness to change",
            "category": "values",
            "percentile": 0.518837869381843,
            "raw_score": 0.7860896827023712,
            "significant": true
        },
        {
            "trait_id": "value_hedonism",
            "name": "Hedonism",
            "category": "values",
            "percentile": 0.06152250500033618,
            "raw_score": 0.6396511576414088,
            "significant": true
        },
        {
            "trait_id": "value_self_enhancement",
            "name": "Self-enhancement",
            "category": "values",
            "percentile": 0.002084466374455529,
            "raw_score": 0.5806327163548453,
            "significant": true
        },
        {
            "trait_id": "value_self_transcendence",
            "name": "Self-transcendence",
            "category": "values",
            "percentile": 0.25311952155085776,
            "raw_score": 0.8221322343758561,
            "significant": true
        }
    ],
    "warnings": []
}